{"generated": "2026-07-09 00:47", "region": "남아시아", "countries": 2, "localized": true, "axes": {"weekly": {"generated": "2026-07-09 00:47", "text": "## 시장 구조\n- **인도** 배틀로열(**BGMI**)·AR 위치기반(**Pokémon GO**)·보드/코인푸시(**Coin Master**), **파키스탄** 캐주얼 보드(**Ludo STAR**)·배틀로열(**PUBG MOBILE**)·4X 전략(**화이트아웃 서바이벌**) 축.\n- 두 나라 모두 매치3(**캔디크러쉬사가**)가 상위 고정, 저과금·대중 트래픽 기반 롱런작이 순위 방어 중.\n- 인도는 현지 특화 배틀로열 **BGMI**(크래프톤 인도 전용 버전)가 상단 점유, 파키스탄은 **Ludo STAR**·**PUBG MOBILE** 등 초대중 소셜·배틀로열이 매출 상단 좌우.\n- 4X·베이스빌더(**Kingshot**, **화이트아웃 서바이벌**, **클래시 오브 클랜**, **탑 워**)가 양국 상단에 다수 진입, 고ARPPU BM이 매출 순위를 끌어올리는 구조.\n\n## 주요 게임·퍼블리셔\n- 인도 1위 **Pokémon GO**(나이언틱, AR 위치기반), 2위 **BGMI**(크래프톤), 파키스탄 1위 **Ludo STAR**(캐주얼 보드), 2위 **PUBG MOBILE**(텐센트·크래프톤).\n- 매출 상위는 라이브 운영 성숙작 위주. **Coin Master**·**캔디크러쉬사가**는 이벤트·시즌 콘텐츠로 잔존 과금 유지, **클래시 오브 클랜**(슈퍼셀)은 장기 롱런 베이스빌더.\n- 4X 강자 다수 포진: **화이트아웃 서바이벌**(센추리게임즈), **Kingshot**·**탑 워** 등 서버 경쟁·연맹전 BM으로 고매출 확보.\n- 파키스탄 급상승 3종(**Marvel 올스타 배틀**, **원신**, **탑 워**)은 각각 가챠 파이팅·오픈월드 가챠 RPG·4X로 장르 분산, 특정 퍼블리셔 독점보다 멀티 장르 경쟁 양상.\n\n## 주요 순위 변동\n- 파키스탄에서 **원신**(▲36.4) 급상승, 신규 배너·이벤트 사이클 진입이 과금 견인.\n- \n버전 6.7 Phase 1 배너는 Sandrone과 Citlali로 7월 1일부터 21일까지 진행\n, 배너 리셋 타이밍이 매출 스파이크로 연결된 것으로 보임.\n- **Marvel 올스타 배틀**(**Marvel Contest of Champions**, 카밤·넷마블 산하)이 ▲46.1로 최대 상승폭. \n해당 게임은 MCU 영화 일정에 맞춰 신규 캐릭터·이벤트를 릴리스하며, 다운로드·매출 스파이크가 영화 개봉 2~4주 전 프로모션과 밀접하게 연동되는 라이브 운영 패턴\n, 이번 급상승도 신규 챔피언·이벤트 사이클로 추정(신뢰 매체의 당주 원인 보도는 미확인).\n- 4X **탑 워**(▲36.2) 동반 상승, 시즌 이벤트·과금 프로모션 정황.\n- 급하락: **Kingdom Guard**(▼45.0, 타워디펜스), **Jackpot World**(▼42.5, 카지노 슬롯), **Dream Cricket 2025**(▼40.8, 크리켓 스포츠). 크리켓 IP 하락은 대회·시즌 이벤트 종료 후 트래픽 역풍 정황.\n\n## 장르 기회\n- 4X·베이스빌더가 양국 상단 다수 점유, 고ARPPU BM으로 매출은 크나 경쟁 강도·UA 단가 높은 포화 구간. 후발 진입 시 차별화 콘텐츠·현지 연맹 커뮤니티 필수.\n- 캐주얼 보드(**Ludo STAR**)·매치3(**캔디크러쉬사가**)·코인푸시(**Coin Master**)는 대중 트래픽 기반 롱런, 신규작이 뚫기 어려운 방어선.\n- 상대적 틈새: 크리켓·스포츠 IP는 남아시아 문화 적합도 높으나 **Dream Cricket 2025** 하락에서 보듯 시즌 의존도 커 상시 콘텐츠·라이브 운영 부실 시 급락 리스크.\n- 가챠 RPG(**원신**, **Marvel 올스타 배틀**)는 IP·배너 사이클로 스파이크형 매출 확보 가능, 글로벌 IP·정기 업데이트 역량 있는 퍼블리셔에 유리.\n\n## 핵심 시사점\n- 남아시아 매출은 배틀로열(현지화)·4X·캐주얼 보드 3축이 좌우, 진출 전략은 장르별 차별화가 관건.\n- 인도는 **BGMI**형 현지 전용 버전·규제 대응 퍼블리싱이 필수, 글로벌 원빌드보다 현지 파트너십·심의 대응 우선.\n- 4X는 매출 상단이나 포화·경쟁 강도 최상위, 후발작은 UA 효율·리텐션 검증 없이는 순위 방어 난이도 높음.\n- 스파이크형 매출(가챠 RPG **원신**·**Marvel 올스타 배틀**)은 배너·IP 이벤트 캘린더 정교화가 핵심, 정기 업데이트 주기와 프로모션 동기화로 순위 방어 벤치마크.\n- 크리켓 등 현지 스포츠 IP는 시즌 이벤트 의존 탈피가 관건, 상시 라이브 콘텐츠로 트래픽 급락 방어 설계 필요.", "pv": "v12-brief5", "history": [{"date": "2026-07-02", "generated": "2026-07-02 21:09", "text": "## 시장 구조\n- **남아시아**는 **배틀로열/슈터**(**PUBG MOBILE**·**BGMI**)와 **보드/Ludo**(**Ludo STAR**·**Yalla Ludo**), 캐주얼 매치3·코인루터가 매출 상단을 분점, 하드코어 전략(**클래시 오브 클랜**·**킹샷**)이 뒤를 받침.\n- **인도**는 **Pokémon GO**(Geolocation AR)·**BGMI**(**Krafton**)·**Coin Master**(코인루터)·**클래시 오브 클랜**(베이스빌딩)·**킹샷**(4X)까지 장르가 폭넓게 섞인 구조, 특정 장르 독점보다 IP·라이브 운영 강자들이 순위 방어.\n- **파키스탄**은 **Ludo STAR**·**Yalla Ludo** 등 로컬 정서 강한 **보드/Ludo** 장르가 최상단, 여기에 **PUBG MOBILE**·**클래시 오브 클랜**·**캔디크러쉬사가** 글로벌 롱런작이 상위 포진.\n- 두 시장 모두 자국 개발 신작보다 글로벌 퍼블리셔 롱런 IP가 매출을 좌우, \n인도는 가장 빠르게 성장하는 추적 국가로 2030년 약 20억 달러 시장으로 전망\n.\n\n## 주요 게임·퍼블리셔\n- **인도**는 **Pokémon GO**·**BGMI** 양강, **파키스탄**은 **Ludo STAR**·**PUBG MOBILE** 양강, 공통분모는 **Tencent**·**Krafton**의 슈터 IP와 **Supercell**·**King**·**Moon Active**의 캐주얼 롱런작.\n- **PUBG MOBILE**은 대형 업데이트로 매출 재점화, \n8주년 대규모 업데이트에 힘입어 IAP 매출이 전분기 대비 128% 급증해 353m 기록\n. 인도판 **BGMI** 역시 동일 엔진·BM으로 슈터 과금 수요 흡수.\n- **Pokémon GO**는 라이브 운영 이벤트로 스파이크를 만드는 전형, \n2026년 기준 포켓몬 IP 모바일 IAP 매출의 53.7%를 Pokémon GO가 차지\n하며 여전히 IP 주력.\n- **킹샷**은 인도 매출 5위 진입, \n화이트아웃 서바이벌로 유명한 중국 스튜디오 Century Games가 개발한 4X 전략작\n. 다만 \n전체 생애 매출의 43%가 미국에서 나오는 미국 편중형\n이라 남아시아는 서브 시장 성격.\n\n## 주요 순위 변동\n- **파키스탄**에서 **포커/카지노**와 **탑 워**(4X)가 동반 급상승, **4X/스포츠/MOBA**는 급하락으로 상반된 흐름.\n- 급상승: \nWSOP Poker(▲34.6), Pokerrrr 2(▲23.2), 탑 워(▲21.7)\n 등 소셜 카지노·포커 트래픽 유입 뚜렷, 라마단·연휴 시즌성 과금 가능성.\n- 급하락: **Infinity Kingdom**(▼33.7)·**EA SPORTS FC 26 Companion**(▼29.0)·**Moba Legends**(▼24.0), 4X·스포츠 컴패니언·MOBA에서 순위 방어 실패.\n- 포커/카지노 급상승의 편집 매체 확인 원인은 데이터 누적 중, 신뢰 보도 확인 시 이벤트·프로모션 근거 보강 필요.\n\n## 장르 기회\n- **포커/소셜 카지노**가 **파키스탄**에서 경쟁 약한데 순위 급등 중인 틈새, 반대로 **4X**·**매치3**·**보드**는 이미 포화.\n- **파키스탄** 포커·카지노 3종 동반 급상승은 현지 결제·과금 수요 대비 공급 얕은 신호, UA 드라이브 대비 안착 여지.\n- **보드/Ludo**(**Ludo STAR**·**Yalla Ludo**)는 로컬 지배력 강해 신규 진입 난도 높음, 차별화 없이는 순위 방어 어려움.\n- **인도**는 \n5월 기준 전 세계 모바일 게임 다운로드의 18.7%(7.03억)를 차지\n하는 초대형 트래픽 풀이나 ARPU 낮아 매출 전환은 IP·라이브 운영 강자 위주, 캐주얼 대량 획득 후 하이브리드 BM 실험 적합.\n\n## 핵심 시사점\n- **남아시아** 진출은 **인도=슈터·IP 라이브 운영**, **파키스탄=보드/Ludo·포커 카지노 틈새**로 국가별 전략 분리가 정답.\n- 벤치마크는 **PUBG MOBILE**의 대형 업데이트발 매출 재점화 공식, \n8주년 업데이트로 전분기 대비 128% 반등\n이 보여주듯 슈터는 콘텐츠 업데이트 주기·이벤트 설계가 매출 순위 방어의 핵심.\n- **Pokémon GO** 사례처럼 IP·라이브 운영 이벤트로 스파이크를 만드는 구조가 유효, \n2026년 2월 말 Road to Kalos 이벤트 출시가 매출 스파이크 요인으로 추정\n되는 등 이벤트 캘린더 현지화가 관건.\n- **파키스탄** 포커/카지노 급상승은 저경쟁 틈새 신호이나 편집 매체 확인 원인은 데이터 누적 중, 시즌성·규제 리스크 검증 후 UA 투입 판단 필요.\n- **인도**는 대량 다운로드 대비 낮은 ARPU 구조라 캐주얼 대량 획득 후 하이브리드 과금으로 LTV를 끌어올리는 현지화 BM이 필수."}, {"date": "2026-06-26", "generated": "2026-06-26 19:12", "text": "## 시장 구조\n- **남아시아**(**인도**·**파키스탄**)는 매출 상위 100위가 전부 **Games**로, 종합앱 대비 게임 트래픽·과금 비중이 절대적인 시장이다.\n- 두 나라 공통으로 **배틀로얄/슈터**(**PUBG MOBILE**·**BATTLEGROUNDS MOBILE INDIA**)와 **캐주얼**(**캔디크러쉬사가**·**Ludo STAR**)이 매출 상단을 양분하고, 여기에 **4X 전략**(**킹샷**·**랜드 오브 제일**·**라스트 Z**)이 가세하는 구도다.\n- 퍼블리셔는 **Tencent**(슈터)·**King**(퍼즐)·**Century Games**(전략)·**Niantic/Scopely**(위치기반)로 글로벌 강자 중심이며, 토종/현지 퍼블리셔 강세는 약하다.\n\n## 핵심 게임·플레이어\n- **인도**는 **Pokémon GO**가 매출 1위로, 라이브 운영(한정 이벤트·콜라보)으로 단기 과금을 끌어올리는 전형적 롱런 IP다. \n위치기반 AR 대표작이자 지속적인 신규 업데이트와 신규 포켓몬으로 모바일 최고 수준의 라이브 운영을 보여주는 타이틀이다.\n\n- **BGMI**(인도)·**PUBG MOBILE**(파키스탄)이 각국 슈터 수요를 흡수하며 매출 상단을 방어 중이다. \nPUBG Mobile은 대규모 8주년 업데이트에 힘입어 IAP 매출이 전분기 대비 128% 급증했다.\n\n- **킹샷**(인도 4위)은 **Century Games**의 신작 4X로 글로벌 모멘텀이 살아있다. \nCentury Games의 킹샷은 출시 1주년에 8억 달러 이상 누적 매출을 기록했고, 2025년 2월 22일 글로벌 출시 후 1년간 양대 마켓에서 약 8억1190만 달러를 벌었다.\n\n\n## 움직임\n- **Pokémon GO**의 매출 1위는 신규 진입이 아니라 이벤트 기반 라이브 운영 스파이크로 보인다. 앞선 사례에서 \nPokémon Go는 전월 대비 61% 매출 성장으로 톱10에 재진입했고, 분석가는 이 급등이 2월 말 출시된 Road to Kalos 이벤트 때문일 가능성이 크다고 봤다.\n\n- **PUBG MOBILE**(파키스탄 1위)의 순위 방어는 대형 기념 업데이트 효과가 이어진 것으로 해석된다(위 8주년 업데이트 참조).\n- 주간 단위 신규 진입·급락에 대한 추가 근거는 데이터 누적 중.\n\n## 장르 기회\n- **4X 전략**은 글로벌 포화·경쟁 강도가 높지만 남아시아에서는 **킹샷**·**라스트 Z**·**랜드 오브 제일**이 동시에 상단에 보이며 아직 현지 안착 여지가 있는 틈새다. \n킹샷은 출시 1년도 안 됐고 4X 서브장르 경쟁이 극심한 상황에서의 성과라는 점이 특기할 만하다.\n\n- **Ludo STAR**(파키스탄 2위)처럼 로컬 친화 캐주얼 보드게임이 상단에 드는 점은 저과금·고리텐션 캐주얼이 이 지역에서 매출까지 연결됨을 보여주는 신호다.\n- 슈터는 **PUBG/BGMI**가 장악해 신규 진입 난도가 높은 포화 영역이다.\n\n## PM 시사점\n- 슈터·전략은 글로벌 강자가 선점한 포화 카테고리이므로, 신규 진출보다 **Pokémon GO**식 한정 이벤트·콜라보 중심 라이브 운영과 **PUBG**식 대형 업데이트 타이밍을 벤치마크해 매출 순위 방어 전략을 짜는 게 현실적이다.\n- 진입을 노린다면 **Ludo STAR** 같은 로컬 친화 캐주얼·보드 장르에서 현지화·결제수단 최적화로 틈새를 공략하는 편이 경쟁 강도 대비 효율적이다."}, {"date": "2026-06-25", "generated": "2026-06-25 05:59", "text": "## 시장 구조\n- **인도**·**파키스탄** 모두 매출 상위가 **배틀로얄**·**캐주얼 퍼즐**·**보드**로 압축됨. **Krafton**이 **BATTLEGROUNDS MOBILE INDIA**·**PUBG MOBILE**로 양국 배틀로얄 매출축을 동시에 쥠.\n- **매치3**·**머지** 계열(**캔디크러쉬사가**·**Gardenscapes**·**가십하버**)이 양국 공통 상위 포진 — 글로벌 검증 BM이 남아시아에서도 그대로 작동.\n- 저ARPU·고다운로드 시장 특성상 상위가 대형 글로벌 퍼블리셔(**King**·**Playrix**·**Moon Active**) 중심으로 형성.\n\n## 핵심 게임·플레이어\n- **인도**는 **Pokémon GO**(IP·라이브 운영)·**BGMI**(배틀로얄)·**eFootball™**(스포츠)·**캔디크러쉬사가**·**Coin Master**로 장르가 분산.\n- **파키스탄**은 지역 친화 보드게임 **Ludo STAR**가 1위 — 글로벌 대작보다 현지·캐주얼 수요가 위에 옴.\n- 양국 공통 강자는 **캔디크러쉬사가**(3위권 고정)와 **Krafton** 배틀로얄 라인업.\n\n## 움직임\n- 단일 주간 스냅샷만 있어 진입·급상승·급하락 비교 불가 — 데이터 누적 중.\n\n## 장르 기회\n- **머지+스토리**(**가십하버**)·메타 진행형 **퍼즐**(**Gardenscapes**)이 매출 안착 — 검증된 캐주얼 BM으로 들어갈 틈새 여전히 유효.\n- **배틀로얄**은 **Krafton** 독식 구도라 포화, 신규 진입 난도 높음.\n- **스포츠**는 **eFootball™** 정도만 상위 — 크리켓 IP 기반 타이틀은 남아시아 트래픽 대비 비어 있는 영역.\n\n## PM 시사점\n- 남아시아 진출 시 **BGMI**식 현지 전용 빌드·규제 대응 현지화가 매출 순위 방어의 1차 벤치마크.\n- 캐주얼 퍼즐·머지는 글로벌 BM 이식이 통하고, **Ludo STAR**처럼 보드·지역 친화 캐주얼은 현지 UA로 빠른 안착을 노릴 만함.\n- 저ARPU 구조이므로 과금 일변도보다 리텐션·광고 BM 병행으로 ARPU 보완."}, {"date": "2026-06-21", "generated": "2026-06-21 02:54", "text": "## 시장 구조\n- 양국 매출 상위가 **배틀로열**과 **캐주얼**(**매치3**·**보드**·**머지**) 두 축으로 집중\n- **Krafton** 계열 배틀로열 IP가 양국 동시 상위 진입(**BATTLEGROUNDS MOBILE INDIA**=**인도**, **PUBG MOBILE**=**파키스탄**)\n- **Century Games**가 **전략 서바이벌**로 양국 모두 침투(**킹샷**, **WOS: 화이트아웃 서바이벌**)\n\n## 핵심 게임·플레이어\n- **캔디크러쉬사가**(**King**)는 양국 공통 상위로 지역 캐주얼 수요를 대표\n- **인도**: **Pokémon GO**(**Niantic**), **Coin Master**(**Moon Active**) 등 글로벌 대작이 매출 견인\n- **파키스탄**: 로컬 정서의 **Ludo STAR** 1위로 보드게임 문화 강세\n\n## 움직임\n- **전략 서바이벌**(**킹샷**, **WOS: 화이트아웃 서바이벌**)·**머지**(**가십하버**) 신흥 타이틀이 상위 진입\n- 배틀로열은 **인도** 현지화판(**BATTLEGROUNDS MOBILE INDIA**)과 **파키스탄** 글로벌판(**PUBG MOBILE**)으로 갈림\n- **Ludo STAR**·**Pokémon GO**는 국가별 편중 — 표본 2개국, 데이터 누적 중\n\n## 장르 기회\n- **머지/스토리**(**가십하버**)는 **파키스탄**에만 노출, **인도** 확장 여지\n- **매치3**·**배틀로열**은 강자 선점으로 포화, 신규 진입 난도 높음\n- 상승세의 **전략 서바이벌**은 추가 진입 여지 존재\n\n## PM 시사점\n- **배틀로열**·**매치3** 정면승부보다 **전략 서바이벌**·**머지** 트렌드에 올라타고, **Ludo STAR**식 로컬 보드·소셜 코드로 현지화하라"}]}, "monthly": {"generated": "2026-07-09 00:47", "text": "## 시장 구조\n- **4X**(6종)·**매치3**(5종) 상위30 최다 점유, **BATTLEGROUNDS MOBILE INDIA**(배틀로얄) 국민 게임급 매출 상위 고정.\n- 장르 분포 상위: **4X** 6, **매치3** 5, **보드** 3, **시뮬 스포츠** 3, **머지** 3, **배틀로얄** 2. 전략과 캐주얼 퍼즐이 양대 축.\n- 매출 최상단은 **Geolocation Games**의 **Pokémon GO**(위치기반)와 **배틀로얄**이 선점, 캐주얼(매치3·코인루터·머지)이 중상위 대량 포진.\n- 인도 중심 **배틀로얄** 특수와 글로벌 캐주얼·4X 라인업이 공존하는 이원 구조.\n\n## 주요 게임·퍼블리셔\n- 매출 1위권 **Pokémon GO**(IP 위치기반), 2위권 **BATTLEGROUNDS MOBILE INDIA**(현지화 배틀로얄) 쌍끌이.\n- **캔디크러쉬사가**(매치3), **Coin Master**(코인루터), 킹샷 **Kingshot**(4X)이 중상위 매출 형성, 글로벌 롱런 타이틀 위주.\n- 퍼블리셔 다양성 높음(**Geolocation Games**, King, Moon Active 계열 캐주얼), 특정 대형사 독점 아닌 분산 구조.\n- 상위 게임 대부분 검증된 라이브 서비스 IP, 신작보다 롱런 타이틀의 매출 방어가 지배적.\n\n## 주요 순위 변동\n- 데이터 누적 중(단일 구간, 급상승·급하락 집계 없음).\n- 기간 1구간(2026-06)만 확보, 진입·이탈 추세 판단 불가.\n- 차기 스냅샷 확보 시 **4X**·**매치3** 신작 모멘텀과 순위 방어 여부 재확인 필요.\n\n## 장르 기회\n- **4X**(6종) 상위30 최다이나 매출 최상단은 배틀로얄·위치기반이 선점, **4X** 내부 경쟁 포화.\n- 매출 TOP5 중 캐주얼 3종(**매치3**·**코인루터**·**머지**) 안착, 저CPI·광범위 리텐션 기반 캐주얼 여전히 유효.\n- **시뮬 스포츠**(3종) 소수 포진, 크리켓 등 현지 스포츠 IP 연계 시 틈새 여지.\n- **배틀로얄**은 **BATTLEGROUNDS MOBILE INDIA** 독주로 신규 진입 장벽 높음, 정면 경쟁 비권장.\n\n## 핵심 시사점\n- 인도 배틀로얄 독주·글로벌 캐주얼 안착 구조에서 **4X**·**매치3** 라이브 운영형 진입이 현실적.\n- 진출 시 **BATTLEGROUNDS MOBILE INDIA** 정면 대결 회피, **4X**·**매치3**·**머지** 등 검증 장르로 UA 효율과 리텐션 확보 우선.\n- 현지화는 인도 결제·저사양 디바이스·언어 대응 필수, 크리켓 등 로컬 스포츠 IP 콜라보로 차별화.\n- 단일 구간 데이터로 추세 미확정, 다음 스냅샷에서 신작 모멘텀·급상승 트래킹 후 UA 드라이브 타이밍 결정.", "pv": "v12-brief5", "history": [{"date": "2026-07-02", "generated": "2026-07-02 21:09", "text": "## 시장 구조\n- **남아시아** 매출 상위 장르는 **4X** 6종·**매치3** 5종 양강, **보드**·**시뮬 스포츠**·**머지** 각 3종으로 뒤 잇는 분산 구조.\n- 상위30 장르 합산에서 **4X**(6)와 **매치3**(5)가 11종으로 전체의 약 1/3 차지, 전략과 캐주얼 퍼즐이 매출 축.\n- **배틀로얄**은 2종에 그치나 로컬 IP **BATTLEGROUNDS MOBILE INDIA**가 전체 2위로 상위권 실매출 견인.\n- 위치기반 수집형 **Pokémon GO**가 전체 1위, 단일 글로벌 IP가 지역 톱 점유.\n\n## 주요 게임·퍼블리셔\n- 매출 1위 **Pokémon GO**(**Geolocation Games**), 2위 **BATTLEGROUNDS MOBILE INDIA**(**배틀로얄**), 캐주얼·전략 혼재.\n- **Pokémon GO**는 위치기반 수집·이벤트 라이브 운영 기반, 글로벌 IP 파워로 지역 최상위 매출.\n- **BATTLEGROUNDS MOBILE INDIA**는 인도 현지화 배틀로얄, 로컬 특화 퍼블리싱으로 2위 안착.\n- 캐주얼 라인업으로 **캔디크러쉬사가**(**매치3**)·**Coin Master**(**코인루터**) 상위, 보드형 슬롯 루팅 BM의 롱런 확인.\n- 전략 신작 **킹샷:Kingshot**(**4X**)이 5위권 진입, 4X 다수 종과 함께 전략 카테고리 매출 두께.\n\n## 주요 순위 변동\n- 급상승·급하락 표기 없음, 단일 구간 스냅샷으로 추세 판단 근거 부족.\n- 데이터 누적 중.\n- 다음 구간 확보 시 신작 **킹샷:Kingshot** 순위 방어·상승 여부 추적 필요.\n\n## 장르 기회\n- **4X** 6종 포화 경쟁, 신규 진입은 차별화 BM·현지화 없이는 순위 방어 난이도 높음.\n- **매치3** 5종도 포화, **캔디크러쉬사가** 등 기존 강자 롱런으로 신작 안착 여지 좁음.\n- **머지** 3종은 매치3 대비 종수 적고 상위 노출, 캐주얼 틈새로 UA 효율 노려볼 구간.\n- **시뮬 스포츠** 3종, 크리켓 등 남아시아 로컬 스포츠 IP 연계 시 현지 트래픽 흡수 가능.\n- **보드** 3종, 로컬 카드·러미류 소셜 카지노형 수요 존재로 진입 검토 대상.\n\n## 핵심 시사점\n- 진출 전략은 글로벌 IP 라이선스 또는 로컬 현지화 배틀로얄·스포츠 둘 중 하나로 명확히 가를 것.\n- **BATTLEGROUNDS MOBILE INDIA** 사례는 로컬 특화 퍼블리싱·현지 IP가 상위 매출 직결임을 입증, 인도 시장 진입 시 현지화 수준이 흥행 좌우.\n- **4X**·**매치3** 포화 구간 신규 진입은 UA 비용 대비 리스크 큼, **머지**·로컬 **시뮬 스포츠**(크리켓)·**보드**를 틈새 후보로 우선 검토.\n- **Pokémon GO**·**Coin Master** 등 라이브 운영·이벤트 주기 기반 롱런작 BM을 벤치마크, 지속 콘텐츠 업데이트로 리텐션·매출 방어 설계 필요."}, {"date": "2026-07-01", "generated": "2026-07-01 07:46", "text": "## 시장 구조\n- 매출 상위는 **4X**(상위30 중 6종)와 **매치3**(5종)이 양대 축, **보드**·**시뮬 스포츠**·**머지** 각 3종이 중위권을 받친다.\n- 글로벌 대형 IP·롱런작(**Pokémon GO**, **캔디크러쉬사가**, **Coin Master**)이 상단을 점유, 현지 색채는 **BATTLEGROUNDS MOBILE INDIA**가 대표한다.\n\n## 핵심 게임·플레이어\n- TOP5가 위치기반(**Pokémon GO**)·배틀로얄(**BATTLEGROUNDS MOBILE INDIA**)·캐주얼 퍼즐(**캔디크러쉬사가**)·코인루터(**Coin Master**)·신흥 **4X**(**킹샷:Kingshot**)로 장르가 분산돼 있다.\n- 인도 시장 특화 타이틀인 **BATTLEGROUNDS MOBILE INDIA**가 1.8위로 트래픽·매출 모두 강세, 현지화·퍼블리싱이 통한 사례다.\n\n## 움직임\n- 1구간 스냅샷이라 진입·급상승·급하락 비교 불가, 데이터 누적 중.\n\n## 장르 기회\n- **4X**가 상위30에 6종으로 가장 두껍지만 TOP5 진입은 **킹샷** 1종뿐, 상단 매출 방어는 아직 열려 있어 신작 모멘텀을 노릴 구간이다.\n- **매치3**·**머지**·**보드**는 종수는 많아 포화 신호, BM 차별화 없이는 신규 진입 난도가 높다.\n\n## PM 시사점\n- 진출 시 **BATTLEGROUNDS MOBILE INDIA**식 현지화·IP 전략을 벤치마크하고, **4X**는 상위 매출 빈틈을 겨냥한 UA 드라이브로 안착을 노릴 것."}]}, "quarterly": {"generated": "2026-07-09 00:47", "text": "## 시장 구조\n- **4X**(상위30 중 6종)·**매치3**(5종) 양강, **BATTLEGROUNDS MOBILE INDIA**(**배틀로얄**) 로컬 IP가 매출 상단 견인.\n- 매출 TOP5가 **지오로케이션**(**Pokémon GO**), **배틀로얄**, **매치3**(**캔디크러쉬사가**), **코인루터**(**Coin Master**), **4X**(**킹샷**)로 장르 분산, 특정 장르 독점 구조 아님.\n- 상위30 장르 꼬리는 **보드** 3종, **시뮬 스포츠** 3종, **머지** 3종으로 캐주얼·중미드코어 혼재.\n- **인도** 시장 특성상 로컬 배틀로얄(**BATTLEGROUNDS MOBILE INDIA**)의 트래픽·과금이 지역 합산 매출에 크게 기여.\n\n## 주요 게임·퍼블리셔\n- 글로벌 대형 IP(**Pokémon GO**, **캔디크러쉬사가**, **Coin Master**)와 로컬 특화작(**BATTLEGROUNDS MOBILE INDIA**)이 매출 상위 공존.\n- **Pokémon GO**(**Geolocation Games**) 매출 1위권, 위치기반 라이브 이벤트로 롱런 유지.\n- **BATTLEGROUNDS MOBILE INDIA**(**배틀로얄**) 현지 규제 대응 리론칭 이후 안착, 지역 로컬라이즈 성공 사례.\n- **King**의 **캔디크러쉬사가**(**매치3**), **Moon Active**의 **Coin Master**(**코인루터**) 등 검증된 캐주얼 BM이 안정적 매출 방어.\n- **킹샷:Kingshot**(**4X**) TOP5 진입, 신흥 **4X** 신작의 남아시아 침투 확인.\n\n## 주요 순위 변동\n- 데이터 누적 중(단일 분기 스냅샷, 급상승·급하락 집계 없음).\n- 관측 구간 1개(2026-Q2)로 분기 간 진입·이탈 비교 불가.\n- 다음 분기 스냅샷 확보 후 **4X**·**매치3** 신작 모멘텀 추적 필요.\n\n## 장르 기회\n- **4X** 포화 초입(상위30 6종), **매치3** 경쟁 심화, 반면 **머지**·**보드**는 소수 진입으로 틈새 여지.\n- **4X**는 **킹샷** 포함 6종 밀집, 신규 진입 시 차별화 BM·현지화 필수, 레드오션화 진행.\n- **매치3** 5종은 **캔디크러쉬사가** 등 글로벌 강자 고착, 신작 안착 난이도 높음.\n- **머지** 3종·**보드** 3종은 상위 밀집도 낮아 캐주얼 신작 틈새 공략 가능.\n- **시뮬 스포츠** 3종은 크리켓 등 지역 스포츠 IP 결합 시 로컬 수요 확보 여지.\n\n## 핵심 시사점\n- 남아시아 진출은 로컬 IP·현지화(**BATTLEGROUNDS MOBILE INDIA** 모델)와 글로벌 캐주얼 BM(**매치3**·**코인루터**) 이원 전략이 유효.\n- **인도** 규제·결제 환경 대응한 로컬 퍼블리싱·리론칭이 매출 안착의 전제 조건.\n- **4X**·**매치3** 레드오션 회피, **머지**·**보드**·**시뮬 스포츠**(크리켓 IP) 틈새로 UA 효율 확보.\n- 벤치마크: **Pokémon GO**의 위치기반 라이브 이벤트, **Coin Master**의 소셜·루팅 BM을 저ARPU 시장에 맞게 광고·소액 과금 병행 설계.\n- 단일 분기 데이터인 만큼 신작 모멘텀·순위 변동은 차기 스냅샷으로 검증 후 투자 판단.", "pv": "v12-brief5", "history": [{"date": "2026-07-02", "generated": "2026-07-02 21:09", "text": "## 시장 구조\n- **4X** 6종, **매치3** 5종 양대 축, **배틀로얄** BGMI가 로컬 IP로 상위권 방어.\n- 상위30 장르분포: **4X** 6, **매치3** 5, **보드** 3, **시뮬 스포츠** 3, **머지** 3, **배틀로얄** 2로 전략과 캐주얼 퍼즐이 병존.\n- 매출 TOP5에 **Geolocation Games**(Pokémon GO), **배틀로얄**(BGMI), **매치3**(캔디크러쉬사가), **코인루터**(Coin Master), **4X**(킹샷) 각 장르 1종씩 분산, 특정 장르 독점 없음.\n- **인도** 중심 시장 특성상 로컬 배틀로얄 BGMI가 글로벌 캐주얼과 공존하는 이원 구조.\n\n## 주요 게임·퍼블리셔\n- 글로벌 대작(**Pokémon GO**, **캔디크러쉬사가**, **Coin Master**)과 로컬 최적화 배틀로얄(**BGMI**) 혼재.\n- 1위권 **Pokémon GO**(**Geolocation Games**), 위치기반 수집형으로 롱런 라이브 서비스 대표작.\n- **BATTLEGROUNDS MOBILE INDIA**, 현지 규제 대응 리브랜딩 버전으로 인도 시장 전용 배틀로얄 안착.\n- **캔디크러쉬사가**(King), **Coin Master**(Moon Active), **킹샷:Kingshot**(**4X**) 등 글로벌 캐주얼·전략 퍼블리셔가 매출 상위 유지.\n\n## 주요 순위 변동\n- 데이터 누적 중(1개 분기 단일 스냅샷, 급상승·급하락 집계 없음).\n- 비교 대상 이전 분기 부재로 진입·이탈 판별 불가.\n- 다음 분기 데이터 확보 시 순위 추이 해석 가능.\n\n## 장르 기회\n- **4X** 6종 포화 경쟁, **매치3** 5종 안정적 수요, 틈새는 **머지**·**시뮬 스포츠**.\n- **4X**는 킹샷 등 다수 진입으로 UA 경쟁 과열, 신규 진입 시 차별화 BM 필요.\n- **머지** 3종, **보드** 3종은 상위권 진입 여지 있는 중경쟁 구간.\n- **시뮬 스포츠** 3종, 크리켓 등 현지 인기 종목 결합 시 로컬 특화 기회.\n\n## 핵심 시사점\n- **인도** 배틀로얄 로컬라이징(BGMI 모델)과 글로벌 캐주얼 퍼즐 병행이 진출 정공법.\n- BGMI 사례처럼 현지 규제·브랜딩 대응한 별도 버전 퍼블리싱이 시장 안착 핵심.\n- **4X** 포화 대비 **머지**·**시뮬 스포츠**(크리켓) 틈새 공략이 경쟁 강도 대비 유리.\n- 저ARPU 시장 특성상 배틀패스·광고 혼합 BM과 리텐션 중심 라이브 운영으로 롱런 설계.\n- 단일 분기 데이터라 순위 변동 추적을 위한 지속 모니터링 병행 필요."}, {"date": "2026-07-01", "generated": "2026-07-01 07:46", "text": "## 시장 구조\n- **4X 6종·매치3 5종**으로 상위30 매출 장르가 양분 — 글로벌 흥행작이 그대로 차트를 채우는 구조다.\n- 토종 IP **BATTLEGROUNDS MOBILE INDIA**(**배틀로얄**)가 상위권을 지키며, 현지 규제·퍼블리싱이 통하는 인도 시장 특성이 드러난다.\n\n## 핵심 게임·플레이어\n- 1위권 **Pokémon GO**(**위치기반**)는 IP 파워와 야외 트래픽 기반 롱런작, **캔디크러쉬사가**·**Coin Master**는 글로벌 캐주얼 라이브 운영의 매출 방어 사례다.\n- **킹샷:Kingshot**(**4X**)이 상위 진입 — 4X 신작 모멘텀이 이 지역에서도 유효함을 보여준다.\n\n## 움직임\n- 단일 구간 스냅샷이라 진입·급상승·급하락 시그널은 데이터 누적 중.\n\n## 장르 기회\n- **4X**가 상위30 6종으로 포화 진입 단계 — UA 단가·경쟁 강도 부담이 큰 레드오션이다.\n- **보드·머지·시뮬 스포츠**가 각 3종으로 중위권에 안착, 캐주얼·미드코어 틈새 여지가 있다.\n\n## PM 시사점\n- 인도 중심 시장은 토종 퍼블리싱·현지화가 진입 전제 조건 — **4X** 직접 경쟁보다 머지·보드 캐주얼로 UA 효율을 노리는 우회 전략을 검토하라."}]}}, "text": "## 시장 구조\n- **인도** 배틀로열(**BGMI**)·AR 위치기반(**Pokémon GO**)·보드/코인푸시(**Coin Master**), **파키스탄** 캐주얼 보드(**Ludo STAR**)·배틀로열(**PUBG MOBILE**)·4X 전략(**화이트아웃 서바이벌**) 축.\n- 두 나라 모두 매치3(**캔디크러쉬사가**)가 상위 고정, 저과금·대중 트래픽 기반 롱런작이 순위 방어 중.\n- 인도는 현지 특화 배틀로열 **BGMI**(크래프톤 인도 전용 버전)가 상단 점유, 파키스탄은 **Ludo STAR**·**PUBG MOBILE** 등 초대중 소셜·배틀로열이 매출 상단 좌우.\n- 4X·베이스빌더(**Kingshot**, **화이트아웃 서바이벌**, **클래시 오브 클랜**, **탑 워**)가 양국 상단에 다수 진입, 고ARPPU BM이 매출 순위를 끌어올리는 구조.\n\n## 주요 게임·퍼블리셔\n- 인도 1위 **Pokémon GO**(나이언틱, AR 위치기반), 2위 **BGMI**(크래프톤), 파키스탄 1위 **Ludo STAR**(캐주얼 보드), 2위 **PUBG MOBILE**(텐센트·크래프톤).\n- 매출 상위는 라이브 운영 성숙작 위주. **Coin Master**·**캔디크러쉬사가**는 이벤트·시즌 콘텐츠로 잔존 과금 유지, **클래시 오브 클랜**(슈퍼셀)은 장기 롱런 베이스빌더.\n- 4X 강자 다수 포진: **화이트아웃 서바이벌**(센추리게임즈), **Kingshot**·**탑 워** 등 서버 경쟁·연맹전 BM으로 고매출 확보.\n- 파키스탄 급상승 3종(**Marvel 올스타 배틀**, **원신**, **탑 워**)은 각각 가챠 파이팅·오픈월드 가챠 RPG·4X로 장르 분산, 특정 퍼블리셔 독점보다 멀티 장르 경쟁 양상.\n\n## 주요 순위 변동\n- 파키스탄에서 **원신**(▲36.4) 급상승, 신규 배너·이벤트 사이클 진입이 과금 견인.\n- \n버전 6.7 Phase 1 배너는 Sandrone과 Citlali로 7월 1일부터 21일까지 진행\n, 배너 리셋 타이밍이 매출 스파이크로 연결된 것으로 보임.\n- **Marvel 올스타 배틀**(**Marvel Contest of Champions**, 카밤·넷마블 산하)이 ▲46.1로 최대 상승폭. \n해당 게임은 MCU 영화 일정에 맞춰 신규 캐릭터·이벤트를 릴리스하며, 다운로드·매출 스파이크가 영화 개봉 2~4주 전 프로모션과 밀접하게 연동되는 라이브 운영 패턴\n, 이번 급상승도 신규 챔피언·이벤트 사이클로 추정(신뢰 매체의 당주 원인 보도는 미확인).\n- 4X **탑 워**(▲36.2) 동반 상승, 시즌 이벤트·과금 프로모션 정황.\n- 급하락: **Kingdom Guard**(▼45.0, 타워디펜스), **Jackpot World**(▼42.5, 카지노 슬롯), **Dream Cricket 2025**(▼40.8, 크리켓 스포츠). 크리켓 IP 하락은 대회·시즌 이벤트 종료 후 트래픽 역풍 정황.\n\n## 장르 기회\n- 4X·베이스빌더가 양국 상단 다수 점유, 고ARPPU BM으로 매출은 크나 경쟁 강도·UA 단가 높은 포화 구간. 후발 진입 시 차별화 콘텐츠·현지 연맹 커뮤니티 필수.\n- 캐주얼 보드(**Ludo STAR**)·매치3(**캔디크러쉬사가**)·코인푸시(**Coin Master**)는 대중 트래픽 기반 롱런, 신규작이 뚫기 어려운 방어선.\n- 상대적 틈새: 크리켓·스포츠 IP는 남아시아 문화 적합도 높으나 **Dream Cricket 2025** 하락에서 보듯 시즌 의존도 커 상시 콘텐츠·라이브 운영 부실 시 급락 리스크.\n- 가챠 RPG(**원신**, **Marvel 올스타 배틀**)는 IP·배너 사이클로 스파이크형 매출 확보 가능, 글로벌 IP·정기 업데이트 역량 있는 퍼블리셔에 유리.\n\n## 핵심 시사점\n- 남아시아 매출은 배틀로열(현지화)·4X·캐주얼 보드 3축이 좌우, 진출 전략은 장르별 차별화가 관건.\n- 인도는 **BGMI**형 현지 전용 버전·규제 대응 퍼블리싱이 필수, 글로벌 원빌드보다 현지 파트너십·심의 대응 우선.\n- 4X는 매출 상단이나 포화·경쟁 강도 최상위, 후발작은 UA 효율·리텐션 검증 없이는 순위 방어 난이도 높음.\n- 스파이크형 매출(가챠 RPG **원신**·**Marvel 올스타 배틀**)은 배너·IP 이벤트 캘린더 정교화가 핵심, 정기 업데이트 주기와 프로모션 동기화로 순위 방어 벤치마크.\n- 크리켓 등 현지 스포츠 IP는 시즌 이벤트 의존 탈피가 관건, 상시 라이브 콘텐츠로 트래픽 급락 방어 설계 필요.", "history": [{"date": "2026-07-02", "generated": "2026-07-02 21:09", "text": "## 시장 구조\n- **남아시아**는 **배틀로열/슈터**(**PUBG MOBILE**·**BGMI**)와 **보드/Ludo**(**Ludo STAR**·**Yalla Ludo**), 캐주얼 매치3·코인루터가 매출 상단을 분점, 하드코어 전략(**클래시 오브 클랜**·**킹샷**)이 뒤를 받침.\n- **인도**는 **Pokémon GO**(Geolocation AR)·**BGMI**(**Krafton**)·**Coin Master**(코인루터)·**클래시 오브 클랜**(베이스빌딩)·**킹샷**(4X)까지 장르가 폭넓게 섞인 구조, 특정 장르 독점보다 IP·라이브 운영 강자들이 순위 방어.\n- **파키스탄**은 **Ludo STAR**·**Yalla Ludo** 등 로컬 정서 강한 **보드/Ludo** 장르가 최상단, 여기에 **PUBG MOBILE**·**클래시 오브 클랜**·**캔디크러쉬사가** 글로벌 롱런작이 상위 포진.\n- 두 시장 모두 자국 개발 신작보다 글로벌 퍼블리셔 롱런 IP가 매출을 좌우, \n인도는 가장 빠르게 성장하는 추적 국가로 2030년 약 20억 달러 시장으로 전망\n.\n\n## 주요 게임·퍼블리셔\n- **인도**는 **Pokémon GO**·**BGMI** 양강, **파키스탄**은 **Ludo STAR**·**PUBG MOBILE** 양강, 공통분모는 **Tencent**·**Krafton**의 슈터 IP와 **Supercell**·**King**·**Moon Active**의 캐주얼 롱런작.\n- **PUBG MOBILE**은 대형 업데이트로 매출 재점화, \n8주년 대규모 업데이트에 힘입어 IAP 매출이 전분기 대비 128% 급증해 353m 기록\n. 인도판 **BGMI** 역시 동일 엔진·BM으로 슈터 과금 수요 흡수.\n- **Pokémon GO**는 라이브 운영 이벤트로 스파이크를 만드는 전형, \n2026년 기준 포켓몬 IP 모바일 IAP 매출의 53.7%를 Pokémon GO가 차지\n하며 여전히 IP 주력.\n- **킹샷**은 인도 매출 5위 진입, \n화이트아웃 서바이벌로 유명한 중국 스튜디오 Century Games가 개발한 4X 전략작\n. 다만 \n전체 생애 매출의 43%가 미국에서 나오는 미국 편중형\n이라 남아시아는 서브 시장 성격.\n\n## 주요 순위 변동\n- **파키스탄**에서 **포커/카지노**와 **탑 워**(4X)가 동반 급상승, **4X/스포츠/MOBA**는 급하락으로 상반된 흐름.\n- 급상승: \nWSOP Poker(▲34.6), Pokerrrr 2(▲23.2), 탑 워(▲21.7)\n 등 소셜 카지노·포커 트래픽 유입 뚜렷, 라마단·연휴 시즌성 과금 가능성.\n- 급하락: **Infinity Kingdom**(▼33.7)·**EA SPORTS FC 26 Companion**(▼29.0)·**Moba Legends**(▼24.0), 4X·스포츠 컴패니언·MOBA에서 순위 방어 실패.\n- 포커/카지노 급상승의 편집 매체 확인 원인은 데이터 누적 중, 신뢰 보도 확인 시 이벤트·프로모션 근거 보강 필요.\n\n## 장르 기회\n- **포커/소셜 카지노**가 **파키스탄**에서 경쟁 약한데 순위 급등 중인 틈새, 반대로 **4X**·**매치3**·**보드**는 이미 포화.\n- **파키스탄** 포커·카지노 3종 동반 급상승은 현지 결제·과금 수요 대비 공급 얕은 신호, UA 드라이브 대비 안착 여지.\n- **보드/Ludo**(**Ludo STAR**·**Yalla Ludo**)는 로컬 지배력 강해 신규 진입 난도 높음, 차별화 없이는 순위 방어 어려움.\n- **인도**는 \n5월 기준 전 세계 모바일 게임 다운로드의 18.7%(7.03억)를 차지\n하는 초대형 트래픽 풀이나 ARPU 낮아 매출 전환은 IP·라이브 운영 강자 위주, 캐주얼 대량 획득 후 하이브리드 BM 실험 적합.\n\n## 핵심 시사점\n- **남아시아** 진출은 **인도=슈터·IP 라이브 운영**, **파키스탄=보드/Ludo·포커 카지노 틈새**로 국가별 전략 분리가 정답.\n- 벤치마크는 **PUBG MOBILE**의 대형 업데이트발 매출 재점화 공식, \n8주년 업데이트로 전분기 대비 128% 반등\n이 보여주듯 슈터는 콘텐츠 업데이트 주기·이벤트 설계가 매출 순위 방어의 핵심.\n- **Pokémon GO** 사례처럼 IP·라이브 운영 이벤트로 스파이크를 만드는 구조가 유효, \n2026년 2월 말 Road to Kalos 이벤트 출시가 매출 스파이크 요인으로 추정\n되는 등 이벤트 캘린더 현지화가 관건.\n- **파키스탄** 포커/카지노 급상승은 저경쟁 틈새 신호이나 편집 매체 확인 원인은 데이터 누적 중, 시즌성·규제 리스크 검증 후 UA 투입 판단 필요.\n- **인도**는 대량 다운로드 대비 낮은 ARPU 구조라 캐주얼 대량 획득 후 하이브리드 과금으로 LTV를 끌어올리는 현지화 BM이 필수."}, {"date": "2026-06-26", "generated": "2026-06-26 19:12", "text": "## 시장 구조\n- **남아시아**(**인도**·**파키스탄**)는 매출 상위 100위가 전부 **Games**로, 종합앱 대비 게임 트래픽·과금 비중이 절대적인 시장이다.\n- 두 나라 공통으로 **배틀로얄/슈터**(**PUBG MOBILE**·**BATTLEGROUNDS MOBILE INDIA**)와 **캐주얼**(**캔디크러쉬사가**·**Ludo STAR**)이 매출 상단을 양분하고, 여기에 **4X 전략**(**킹샷**·**랜드 오브 제일**·**라스트 Z**)이 가세하는 구도다.\n- 퍼블리셔는 **Tencent**(슈터)·**King**(퍼즐)·**Century Games**(전략)·**Niantic/Scopely**(위치기반)로 글로벌 강자 중심이며, 토종/현지 퍼블리셔 강세는 약하다.\n\n## 핵심 게임·플레이어\n- **인도**는 **Pokémon GO**가 매출 1위로, 라이브 운영(한정 이벤트·콜라보)으로 단기 과금을 끌어올리는 전형적 롱런 IP다. \n위치기반 AR 대표작이자 지속적인 신규 업데이트와 신규 포켓몬으로 모바일 최고 수준의 라이브 운영을 보여주는 타이틀이다.\n\n- **BGMI**(인도)·**PUBG MOBILE**(파키스탄)이 각국 슈터 수요를 흡수하며 매출 상단을 방어 중이다. \nPUBG Mobile은 대규모 8주년 업데이트에 힘입어 IAP 매출이 전분기 대비 128% 급증했다.\n\n- **킹샷**(인도 4위)은 **Century Games**의 신작 4X로 글로벌 모멘텀이 살아있다. \nCentury Games의 킹샷은 출시 1주년에 8억 달러 이상 누적 매출을 기록했고, 2025년 2월 22일 글로벌 출시 후 1년간 양대 마켓에서 약 8억1190만 달러를 벌었다.\n\n\n## 움직임\n- **Pokémon GO**의 매출 1위는 신규 진입이 아니라 이벤트 기반 라이브 운영 스파이크로 보인다. 앞선 사례에서 \nPokémon Go는 전월 대비 61% 매출 성장으로 톱10에 재진입했고, 분석가는 이 급등이 2월 말 출시된 Road to Kalos 이벤트 때문일 가능성이 크다고 봤다.\n\n- **PUBG MOBILE**(파키스탄 1위)의 순위 방어는 대형 기념 업데이트 효과가 이어진 것으로 해석된다(위 8주년 업데이트 참조).\n- 주간 단위 신규 진입·급락에 대한 추가 근거는 데이터 누적 중.\n\n## 장르 기회\n- **4X 전략**은 글로벌 포화·경쟁 강도가 높지만 남아시아에서는 **킹샷**·**라스트 Z**·**랜드 오브 제일**이 동시에 상단에 보이며 아직 현지 안착 여지가 있는 틈새다. \n킹샷은 출시 1년도 안 됐고 4X 서브장르 경쟁이 극심한 상황에서의 성과라는 점이 특기할 만하다.\n\n- **Ludo STAR**(파키스탄 2위)처럼 로컬 친화 캐주얼 보드게임이 상단에 드는 점은 저과금·고리텐션 캐주얼이 이 지역에서 매출까지 연결됨을 보여주는 신호다.\n- 슈터는 **PUBG/BGMI**가 장악해 신규 진입 난도가 높은 포화 영역이다.\n\n## PM 시사점\n- 슈터·전략은 글로벌 강자가 선점한 포화 카테고리이므로, 신규 진출보다 **Pokémon GO**식 한정 이벤트·콜라보 중심 라이브 운영과 **PUBG**식 대형 업데이트 타이밍을 벤치마크해 매출 순위 방어 전략을 짜는 게 현실적이다.\n- 진입을 노린다면 **Ludo STAR** 같은 로컬 친화 캐주얼·보드 장르에서 현지화·결제수단 최적화로 틈새를 공략하는 편이 경쟁 강도 대비 효율적이다."}, {"date": "2026-06-25", "generated": "2026-06-25 05:59", "text": "## 시장 구조\n- **인도**·**파키스탄** 모두 매출 상위가 **배틀로얄**·**캐주얼 퍼즐**·**보드**로 압축됨. **Krafton**이 **BATTLEGROUNDS MOBILE INDIA**·**PUBG MOBILE**로 양국 배틀로얄 매출축을 동시에 쥠.\n- **매치3**·**머지** 계열(**캔디크러쉬사가**·**Gardenscapes**·**가십하버**)이 양국 공통 상위 포진 — 글로벌 검증 BM이 남아시아에서도 그대로 작동.\n- 저ARPU·고다운로드 시장 특성상 상위가 대형 글로벌 퍼블리셔(**King**·**Playrix**·**Moon Active**) 중심으로 형성.\n\n## 핵심 게임·플레이어\n- **인도**는 **Pokémon GO**(IP·라이브 운영)·**BGMI**(배틀로얄)·**eFootball™**(스포츠)·**캔디크러쉬사가**·**Coin Master**로 장르가 분산.\n- **파키스탄**은 지역 친화 보드게임 **Ludo STAR**가 1위 — 글로벌 대작보다 현지·캐주얼 수요가 위에 옴.\n- 양국 공통 강자는 **캔디크러쉬사가**(3위권 고정)와 **Krafton** 배틀로얄 라인업.\n\n## 움직임\n- 단일 주간 스냅샷만 있어 진입·급상승·급하락 비교 불가 — 데이터 누적 중.\n\n## 장르 기회\n- **머지+스토리**(**가십하버**)·메타 진행형 **퍼즐**(**Gardenscapes**)이 매출 안착 — 검증된 캐주얼 BM으로 들어갈 틈새 여전히 유효.\n- **배틀로얄**은 **Krafton** 독식 구도라 포화, 신규 진입 난도 높음.\n- **스포츠**는 **eFootball™** 정도만 상위 — 크리켓 IP 기반 타이틀은 남아시아 트래픽 대비 비어 있는 영역.\n\n## PM 시사점\n- 남아시아 진출 시 **BGMI**식 현지 전용 빌드·규제 대응 현지화가 매출 순위 방어의 1차 벤치마크.\n- 캐주얼 퍼즐·머지는 글로벌 BM 이식이 통하고, **Ludo STAR**처럼 보드·지역 친화 캐주얼은 현지 UA로 빠른 안착을 노릴 만함.\n- 저ARPU 구조이므로 과금 일변도보다 리텐션·광고 BM 병행으로 ARPU 보완."}, {"date": "2026-06-21", "generated": "2026-06-21 02:54", "text": "## 시장 구조\n- 양국 매출 상위가 **배틀로열**과 **캐주얼**(**매치3**·**보드**·**머지**) 두 축으로 집중\n- **Krafton** 계열 배틀로열 IP가 양국 동시 상위 진입(**BATTLEGROUNDS MOBILE INDIA**=**인도**, **PUBG MOBILE**=**파키스탄**)\n- **Century Games**가 **전략 서바이벌**로 양국 모두 침투(**킹샷**, **WOS: 화이트아웃 서바이벌**)\n\n## 핵심 게임·플레이어\n- **캔디크러쉬사가**(**King**)는 양국 공통 상위로 지역 캐주얼 수요를 대표\n- **인도**: **Pokémon GO**(**Niantic**), **Coin Master**(**Moon Active**) 등 글로벌 대작이 매출 견인\n- **파키스탄**: 로컬 정서의 **Ludo STAR** 1위로 보드게임 문화 강세\n\n## 움직임\n- **전략 서바이벌**(**킹샷**, **WOS: 화이트아웃 서바이벌**)·**머지**(**가십하버**) 신흥 타이틀이 상위 진입\n- 배틀로열은 **인도** 현지화판(**BATTLEGROUNDS MOBILE INDIA**)과 **파키스탄** 글로벌판(**PUBG MOBILE**)으로 갈림\n- **Ludo STAR**·**Pokémon GO**는 국가별 편중 — 표본 2개국, 데이터 누적 중\n\n## 장르 기회\n- **머지/스토리**(**가십하버**)는 **파키스탄**에만 노출, **인도** 확장 여지\n- **매치3**·**배틀로열**은 강자 선점으로 포화, 신규 진입 난도 높음\n- 상승세의 **전략 서바이벌**은 추가 진입 여지 존재\n\n## PM 시사점\n- **배틀로열**·**매치3** 정면승부보다 **전략 서바이벌**·**머지** 트렌드에 올라타고, **Ludo STAR**식 로컬 보드·소셜 코드로 현지화하라"}]}